aindex/__init__.py
aindex/cli.py
aindex/bin/build_13mer_hash
aindex/bin/compute_aindex
aindex/bin/compute_aindex.py
aindex/bin/compute_aindex13
aindex/bin/compute_index
aindex/bin/compute_index.py
aindex/bin/compute_mphf_seq
aindex/bin/compute_reads
aindex/bin/count_kmers13
aindex/bin/generate_all_13mers
aindex/bin/kmer_counter
aindex/bin/reads_to_fasta.py
aindex/core/__init__.py
aindex/core/aindex.py
aindex/core/aindex_cpp.cpython-39-darwin.so
aindex/core/aindex_cpp_fallback.py
aindex2-1.4.4.dist-info/LICENSE
aindex2-1.4.4.dist-info/METADATA
aindex2-1.4.4.dist-info/WHEEL
aindex2-1.4.4.dist-info/entry_points.txt
aindex2-1.4.4.dist-info/top_level.txt
aindex2-1.4.4.dist-info/RECORD
