Metadata-Version: 2.1
Name: aindex2
Version: 1.4.4
Summary: Perfect hash based index for genome data.
Home-page: https://github.com/ad3002/aindex
Author: Aleksey Komissarov
Author-email: ad3002@gmail.com
Classifier: Programming Language :: Python :: 3
Classifier: Programming Language :: Python :: 3.8
Classifier: Programming Language :: Python :: 3.9
Classifier: Programming Language :: Python :: 3.10
Classifier: Programming Language :: Python :: 3.11
Classifier: Programming Language :: Python :: 3.12
Classifier: Programming Language :: C++
Classifier: Operating System :: POSIX :: Linux
Classifier: Operating System :: MacOS
Requires-Python: >=3.8
License-File: LICENSE
Requires-Dist: numpy>=1.20.0
Requires-Dist: intervaltree==3.1.0
Requires-Dist: editdistance==0.8.1
Requires-Dist: psutil>=5.8.0
